{
    "languages": [
        "en"
    ],
    "filetype": "pdf",
    "toc": [],
    "pages": 25,
    "ocr_stats": {
        "ocr_pages": 2,
        "ocr_failed": 0,
        "ocr_success": 2,
        "ocr_engine": "surya"
    },
    "block_stats": {
        "header_footer": 24,
        "code": 0,
        "table": 0,
        "equations": {
            "successful_ocr": 13,
            "unsuccessful_ocr": 1,
            "equations": 14
        }
    },
    "postprocess_stats": {
        "edit": {}
    }
}